babelvec/__init__.py
babelvec/cli.py
babelvec/families.py
babelvec/core/__init__.py
babelvec/core/fasttext_wrapper.py
babelvec/core/model.py
babelvec/core/positional_encoding.py
babelvec/core/sentence_encoder.py
babelvec/evaluation/__init__.py
babelvec/evaluation/intrinsic.py
babelvec/evaluation/retrieval_eval.py
babelvec/evaluation/sts_eval.py
babelvec/training/__init__.py
babelvec/training/config.py
babelvec/training/monolingual.py
babelvec/training/multilingual.py
babelvec/training/alignment/__init__.py
babelvec/training/alignment/base.py
babelvec/training/alignment/ensemble.py
babelvec/training/alignment/infonce.py
babelvec/training/alignment/procrustes.py
babelvec/utils/__init__.py
babelvec/utils/data_loader.py
babelvec/utils/metrics.py
babelvec/visualization/__init__.py
babelvec/visualization/alignment_viz.py
babelvec/visualization/embedding_space.py
babelvec-0.1.7.dist-info/licenses/LICENSE
babelvec-0.1.7.dist-info/METADATA
babelvec-0.1.7.dist-info/WHEEL
babelvec-0.1.7.dist-info/entry_points.txt
babelvec-0.1.7.dist-info/top_level.txt
babelvec-0.1.7.dist-info/RECORD
