Metadata-Version: 2.4
Name: babelvec
Version: 0.1.7
Summary: Position-aware, cross-lingually aligned word embeddings built on FastText
Author-email: Omar Kamali <babelvec@omarkama.li>
License: MIT
Project-URL: Homepage, https://github.com/omarkamali/babelvec
Project-URL: Documentation, https://github.com/omarkamali/babelvec#readme
Project-URL: Repository, https://github.com/omarkamali/babelvec
Project-URL: Issues, https://github.com/omarkamali/babelvec/issues
Keywords: embeddings,word-embeddings,fasttext,nlp,cross-lingual,multilingual,positional-encoding
Classifier: Development Status :: 4 - Beta
Classifier: Intended Audience :: Developers
Classifier: Intended Audience :: Science/Research
Classifier: License :: OSI Approved :: MIT License
Classifier: Programming Language :: Python :: 3
Classifier: Programming Language :: Python :: 3.10
Classifier: Programming Language :: Python :: 3.11
Classifier: Programming Language :: Python :: 3.12
Classifier: Programming Language :: Python :: 3.13
Classifier: Programming Language :: Python :: 3.14
Classifier: Topic :: Scientific/Engineering :: Artificial Intelligence
Classifier: Topic :: Text Processing :: Linguistic
Requires-Python: >=3.10
License-File: LICENSE
Requires-Dist: numpy>=1.24.0
Requires-Dist: scipy>=1.11.0
Requires-Dist: fasttext>=0.9.2
Requires-Dist: tqdm>=4.66.0
Provides-Extra: dev
Requires-Dist: pytest>=7.4.0; extra == "dev"
Requires-Dist: pytest-cov>=4.1.0; extra == "dev"
Requires-Dist: ruff>=0.1.0; extra == "dev"
Requires-Dist: mypy>=1.5.0; extra == "dev"
Provides-Extra: viz
Requires-Dist: matplotlib>=3.7.0; extra == "viz"
Requires-Dist: seaborn>=0.12.0; extra == "viz"
Requires-Dist: umap-learn>=0.5.3; extra == "viz"
Requires-Dist: scikit-learn>=1.3.0; extra == "viz"
Provides-Extra: all
Requires-Dist: babelvec[dev,viz]; extra == "all"
Dynamic: license-file
